{
    "daily": [
        {
            "Work out plan": {
                "index": 4,
                "tasks": [
                    "squats",
                    "madonna",
                    "Running",
                    "Dead lift"
                ],
                "Complete till": "Running",
                "Streak": 20,
                "Most difficult": {
                    "name": "Running",
                    "score": 4
                },
                "Most easiest": {
                    "name": "Running",
                    "score": 4
                },
                "stops": [
                    "Running",
                    "Running",
                    "Running",
                    "Running"
                ],
                "consistancy": [
                    100,
                    75.0,
                    50,
                    60,
                    75.0,
                    75.0,
                    75.0
                ]
            }
        },
        {
            "Morning Routine": {
                "index": 0,
                "tasks": [
                    "Make bed",
                    "Meditate",
                    "Journal",
                    "Hydrate"
                ],
                "Complete till": "",
                "Streak": 0,
                "Most difficult": {
                    "name": "Meditate",
                    "score": 2
                },
                "Most easiest": {
                    "name": "Meditate",
                    "score": 2
                },
                "stops": [
                    "Meditate",
                    "Meditate",
                    "Journal",
                    "Journal"
                ],
                "consistancy": [
                    75,
                    75,
                    100,
                    100,
                    125.0,
                    125.0,
                    75.0
                ]
            }
        },
        {
            "Skin Care": {
                "index": 0,
                "tasks": [
                    "Cleanser",
                    "Toner",
                    "Serum",
                    "Moisturizer"
                ],
                "Complete till": "",
                "Streak": 0,
                "Most difficult": {
                    "name": "Serum",
                    "score": 1
                },
                "Most easiest": {
                    "name": "Serum",
                    "score": 1
                },
                "stops": [
                    "Serum",
                    "Toner",
                    "Moisturizer",
                    "TEST"
                ],
                "consistancy": [
                    125.0,
                    100,
                    100,
                    100,
                    125.0,
                    125.0,
                    100.0
                ]
            }
        },
        {
            "Night Wind-down": {
                "index": 0,
                "tasks": [
                    "No screens",
                    "Read book",
                    "Stretch",
                    "Plan tomorrow"
                ],
                "Complete till": "",
                "Streak": 0,
                "Most difficult": {
                    "name": "No screens",
                    "score": 2
                },
                "Most easiest": {
                    "name": "No screens",
                    "score": 2
                },
                "stops": [
                    "No screens",
                    "No screens",
                    "Read book",
                    "Read book"
                ],
                "consistancy": [
                    125.0,
                    25,
                    50,
                    50,
                    125.0,
                    125.0,
                    50.0
                ]
            }
        }
    ],
    "weekly": [
        {
            "House Cleaning": {
                "index": 0,
                "tasks": [
                    "Vacuuming",
                    "Mopping",
                    "Dusting",
                    "Bathroom scrub"
                ],
                "Complete till": "",
                "Streak": 0,
                "Most difficult": {
                    "name": "Dusting",
                    "score": 3
                },
                "Most easiest": {
                    "name": "Mopping",
                    "score": 1
                },
                "stops": [
                    "Dusting",
                    "Mopping",
                    "Dusting",
                    "Dusting"
                ],
                "consistancy": [
                    125.0,
                    50,
                    75,
                    125.0
                ]
            }
        },
        {
            "Meal Prep": {
                "index": 0,
                "tasks": [
                    "Inventory check",
                    "Grocery shopping",
                    "Chopping veggies",
                    "Cooking batches"
                ],
                "Complete till": "",
                "Streak": 0,
                "Most difficult": {
                    "name": "Grocery shopping",
                    "score": 1
                },
                "Most easiest": {
                    "name": "Grocery shopping",
                    "score": 1
                },
                "stops": [
                    "Grocery shopping",
                    "Chopping veggies",
                    "Cooking batches",
                    "TEST"
                ],
                "consistancy": [
                    125.0,
                    100,
                    100,
                    125.0
                ]
            }
        },
        {
            "Financial Review": {
                "index": 0,
                "tasks": [
                    "Track expenses",
                    "Update budget",
                    "Pay bills",
                    "Transfer to savings"
                ],
                "Complete till": "",
                "Streak": 0,
                "Most difficult": {
                    "name": "Update budget",
                    "score": 2
                },
                "Most easiest": {
                    "name": "Track expenses",
                    "score": 1
                },
                "stops": [
                    "Update budget",
                    "Track expenses",
                    "Pay bills",
                    "Update budget"
                ],
                "consistancy": [
                    125.0,
                    50,
                    50,
                    125.0
                ]
            }
        },
        {
            "Self-Care Weekend": {
                "index": 0,
                "tasks": [
                    "Long bath",
                    "Hair mask",
                    "Manicure",
                    "Call a friend"
                ],
                "Complete till": "",
                "Streak": 0,
                "Most difficult": {
                    "name": "Hair mask",
                    "score": 2
                },
                "Most easiest": {
                    "name": "Manicure",
                    "score": 1
                },
                "stops": [
                    "Hair mask",
                    "Manicure",
                    "Hair mask",
                    "TEST"
                ],
                "consistancy": [
                    125.0,
                    100,
                    100,
                    125.0
                ]
            }
        }
    ],
    "monthly": [
        {
            "Deep Home Maintenance": {
                "index": 0,
                "tasks": [
                    "Clean AC filters",
                    "Wash curtains",
                    "Wipe windows",
                    "Organize closet"
                ],
                "Complete till": "",
                "Streak": 0,
                "Most difficult": {
                    "name": "Wipe windows",
                    "score": 3
                },
                "Most easiest": {
                    "name": "Wash curtains",
                    "score": 1
                },
                "stops": [
                    "Wipe windows",
                    "Wash curtains",
                    "Wipe windows",
                    "Wipe windows"
                ],
                "consistancy": [
                    125.0,
                    75,
                    50,
                    50,
                    50,
                    125.0,
                    75.0,
                    100,
                    50,
                    50,
                    50,
                    50
                ]
            }
        },
        {
            "Business Goal Tracking": {
                "index": 0,
                "tasks": [
                    "Review Analytics",
                    "Client feedback audit",
                    "Update portfolio",
                    "Set next KPIs"
                ],
                "Complete till": "",
                "Streak": 0,
                "Most difficult": {
                    "name": "Review Analytics",
                    "score": 2
                },
                "Most easiest": {
                    "name": "Client feedback audit",
                    "score": 1
                },
                "stops": [
                    "Review Analytics",
                    "Client feedback audit",
                    "Review Analytics",
                    "TEST"
                ],
                "consistancy": [
                    125.0,
                    50,
                    25,
                    100,
                    100,
                    125.0,
                    25.0,
                    75,
                    100,
                    100,
                    100,
                    100
                ]
            }
        },
        {
            "Car Care": {
                "index": 0,
                "tasks": [
                    "Car wash",
                    "Interior vacuum",
                    "Fluid level check",
                    "Tire pressure check"
                ],
                "Complete till": "",
                "Streak": 0,
                "Most difficult": {
                    "name": "Interior vacuum",
                    "score": 1
                },
                "Most easiest": {
                    "name": "Interior vacuum",
                    "score": 1
                },
                "stops": [
                    "Interior vacuum",
                    "Tire pressure check",
                    "TEST",
                    "Test"
                ],
                "consistancy": [
                    125.0,
                    100,
                    100,
                    50,
                    100,
                    125.0,
                    100.0,
                    100,
                    100,
                    100,
                    100,
                    100
                ]
            }
        },
        {
            "Personal Development": {
                "index": 0,
                "tasks": [
                    "Finish 1 book",
                    "Watch a documentary",
                    "Attend a webinar",
                    "Update resume"
                ],
                "Complete till": "",
                "Streak": 0,
                "Most difficult": {
                    "name": "Watch a documentary",
                    "score": 2
                },
                "Most easiest": {
                    "name": "Attend a webinar",
                    "score": 1
                },
                "stops": [
                    "Watch a documentary",
                    "Attend a webinar",
                    "Update resume",
                    "Watch a documentary"
                ],
                "consistancy": [
                    125.0,
                    75,
                    25,
                    50,
                    0,
                    125.0,
                    50.0,
                    25,
                    50,
                    0,
                    50,
                    25
                ]
            }
        }
    ]
}